emil/__init__.py
emil-0.0.0.dev0.dist-info/METADATA
emil-0.0.0.dev0.dist-info/WHEEL
emil-0.0.0.dev0.dist-info/top_level.txt
emil-0.0.0.dev0.dist-info/RECORD
