Metadata-Version: 2.1
Name: emil
Version: 0.0.0.dev0
Summary: Coming soon!
Author-email: Suzen Fylke <codesue@users.noreply.github.com>
